clip_interrogator/__init__.py
clip_interrogator/clip_interrogator.py
clip_interrogator/data/artists.txt
clip_interrogator/data/flavors.txt
clip_interrogator/data/mediums.txt
clip_interrogator/data/movements.txt
clip_interrogator/data/negative.txt
clip_interrogator-0.6.0.dist-info/LICENSE
clip_interrogator-0.6.0.dist-info/METADATA
clip_interrogator-0.6.0.dist-info/WHEEL
clip_interrogator-0.6.0.dist-info/top_level.txt
clip_interrogator-0.6.0.dist-info/RECORD
