Metadata-Version: 2.1
Name: clip-interrogator
Version: 0.6.0
Summary: Generate a prompt from an image
Home-page: https://github.com/pharmapsychotic/clip-interrogator
Author: pharmapsychotic
Author-email: me@pharmapsychotic.com
License: MIT
Keywords: blip,clip,prompt-engineering,stable-diffusion,text-to-image
Classifier: Intended Audience :: Developers
Classifier: Intended Audience :: Science/Research
Classifier: License :: OSI Approved :: MIT License
Classifier: Topic :: Education
Classifier: Topic :: Scientific/Engineering
Classifier: Topic :: Scientific/Engineering :: Artificial Intelligence
Provides-Extra: dev
License-File: LICENSE
